LICENSE
README.md
setup.py
ali_nls.egg-info/PKG-INFO
ali_nls.egg-info/SOURCES.txt
ali_nls.egg-info/dependency_links.txt
ali_nls.egg-info/requires.txt
ali_nls.egg-info/top_level.txt
nls/__init__.py
nls/core.py
nls/exception.py
nls/logging.py
nls/realtime_meeting.py
nls/speech_recognizer.py
nls/speech_synthesizer.py
nls/speech_transcriber.py
nls/stream_input_tts.py
nls/token.py
nls/util.py
nls/version.py
nls/websocket/__init__.py
nls/websocket/_abnf.py
nls/websocket/_app.py
nls/websocket/_cookiejar.py
nls/websocket/_core.py
nls/websocket/_exceptions.py
nls/websocket/_handshake.py
nls/websocket/_http.py
nls/websocket/_logging.py
nls/websocket/_socket.py
nls/websocket/_ssl_compat.py
nls/websocket/_url.py
nls/websocket/_utils.py