Metadata-Version: 2.1
Name: ali-nls
Version: 1.1.0
Summary: python sdk for nls
Home-page: https://github.com/..
Author: henson
Author-email: henson_wu@foxmail.com
License: Apache License 2.0
Keywords: nls,sdk
Platform: UNKNOWN
Classifier: Programming Language :: Python :: 3
Classifier: License :: OSI Approved :: Apache Software License
Classifier: Operating System :: OS Independent
License-File: LICENSE
